goosync-0.5.0.dist-info/RECORD
goosync-0.5.0.dist-info/METADATA
goosync-0.5.0.dist-info/pbr.json
goosync-0.5.0.dist-info/WHEEL
goosync-0.5.0.dist-info/DESCRIPTION.rst
goosync-0.5.0.dist-info/entry_points.txt
goosync-0.5.0.dist-info/metadata.json
goosync-0.5.0.dist-info/top_level.txt
goosync/goosync.py
goosync/__init__.py
goosync/version.py
