Metadata-Version: 2.0
Name: goosync
Version: 0.5.0
Summary: Google Drive synchronization utility
Home-page: https://bitbucket.org/pnfisher/goosync
Author: Philip Fisher
Author-email: philip.fisher@alumni.utoronto.ca
License: GPLv3
Keywords: google drive synchronization utility
Platform: UNKNOWN
Classifier: Development Status :: 4 - Beta
Classifier: Environment :: Console
Classifier: License :: OSI Approved :: GNU General Public License v3 (GPLv3)
Classifier: Natural Language :: English
Classifier: Operating System :: POSIX :: Linux
Classifier: Programming Language :: Python :: 2.6
Classifier: Programming Language :: Python :: 2.7
Classifier: Programming Language :: Python :: 3.3
Classifier: Programming Language :: Python :: 3.4
Classifier: Topic :: Utilities
Requires-Dist: google-api-python-client
Provides-Extra: test
Requires-Dist: pexpect; extra == 'test'
